{"name":"develop","namedChunkGroups":{"commons":{"name":"commons","assets":[{"name":"framework.js","size":3036082},{"name":"commons.css","size":142227},{"name":"commons.js","size":3557878},{"name":"commons.14084f0e61071d659d8d.hot-update.js","size":873}],"filteredAssets":0,"assetsSize":6737060,"filteredAuxiliaryAssets":23,"auxiliaryAssetsSize":607856},"component---cache-dev-404-page-js":{"name":"component---cache-dev-404-page-js","assets":[{"name":"component---cache-dev-404-page-js.js","size":71883}],"filteredAssets":0,"assetsSize":71883,"filteredAuxiliaryAssets":0,"auxiliaryAssetsSize":0},"component---src-pages-index-tsx":{"name":"component---src-pages-index-tsx","assets":[{"name":"component---src-pages-index-tsx.js","size":8994661},{"name":"component---src-pages-index-tsx.14084f0e61071d659d8d.hot-update.js","size":11419}],"filteredAssets":0,"assetsSize":9006080,"filteredAuxiliaryAssets":0,"auxiliaryAssetsSize":0},"component---src-pages-index-tsxhead":{"name":"component---src-pages-index-tsxhead","assets":[{"name":"component---src-pages-index-tsxhead.js","size":8998597},{"name":"component---src-pages-index-tsxhead.14084f0e61071d659d8d.hot-update.js","size":11423}],"filteredAssets":0,"assetsSize":9010020,"filteredAuxiliaryAssets":0,"auxiliaryAssetsSize":0}},"assetsByChunkName":{"commons":["framework.js","commons.css","commons.js","commons.14084f0e61071d659d8d.hot-update.js"],"component---cache-dev-404-page-js":["component---cache-dev-404-page-js.js"],"component---src-pages-index-tsx":["component---src-pages-index-tsx.js","component---src-pages-index-tsx.14084f0e61071d659d8d.hot-update.js"],"component---src-pages-index-tsxhead":["component---src-pages-index-tsxhead.js","component---src-pages-index-tsxhead.14084f0e61071d659d8d.hot-update.js"]},"childAssetsByChunkName":{}}
